Metadata-Version: 1.0
Name: distributions-a
Version: 0.1
Summary: Gaussian and Binomial distributions
Home-page: UNKNOWN
Author: Alicia Alcaide
Author-email: UNKNOWN
License: UNKNOWN
Platform: UNKNOWN
